oc_cdt_queue2/__init__.py
oc_cdt_queue2/ipc_messages.py
oc_cdt_queue2/queue_application.py
oc_cdt_queue2/queue_base.py
oc_cdt_queue2/queue_client.py
oc_cdt_queue2/queue_connection_prcs.py
oc_cdt_queue2/queue_handler.py
oc_cdt_queue2/queue_rpc.py
oc_cdt_queue2/queue_server.py
oc_cdt_queue2/test/__init__.py
oc_cdt_queue2/test/test_app.py
oc_cdt_queue2/test/test_base.py
oc_cdt_queue2/test/test_client.py
oc_cdt_queue2/test/test_connection_prcs.py
oc_cdt_queue2/test/test_handler.py
oc_cdt_queue2/test/test_qrpc.py
oc_cdt_queue2/test/test_server.py
oc_cdt_queue2/test/mocks/__init__.py
oc_cdt_queue2/test/mocks/queue_t.py
oc_cdt_queue2/test/synchron/__init__.py
oc_cdt_queue2/test/synchron/test_app.py
oc_cdt_queue2/test/synchron/test_base.py
oc_cdt_queue2/test/synchron/test_handler.py
oc_cdt_queue2/test/synchron/test_recv.py
oc_cdt_queue2/test/synchron/test_rpc.py
oc_cdt_queue2/test/synchron/test_send.py
oc_cdt_queue2/test/synchron/mocks/__init__.py
oc_cdt_queue2/test/synchron/mocks/queue_application.py
oc_cdt_queue2/test/synchron/mocks/queue_base.py
oc_cdt_queue2/test/synchron/mocks/queue_client.py
oc_cdt_queue2/test/synchron/mocks/queue_handler.py
oc_cdt_queue2/test/synchron/mocks/queue_loopback.py
oc_cdt_queue2/test/synchron/mocks/queue_rpc.py
oc_cdt_queue2/test/synchron/mocks/queue_server.py
oc_cdt_queue2-4.1.3.dist-info/licenses/LICENSE
oc_cdt_queue2-4.1.3.dist-info/METADATA
oc_cdt_queue2-4.1.3.dist-info/WHEEL
oc_cdt_queue2-4.1.3.dist-info/top_level.txt
oc_cdt_queue2-4.1.3.dist-info/RECORD
