Metadata-Version: 2.4
Name: oc-cdt-queue2
Version: 4.1.3
Summary: Code for Deliveries-related message queues management
License: Apache2.0
Requires-Python: >=3.6
License-File: LICENSE
Requires-Dist: pika
Dynamic: description-content-type
Dynamic: license
Dynamic: license-file
Dynamic: requires-dist
Dynamic: requires-python
Dynamic: summary
